Workbook
Name Slicer_Payment_Frequency: #N/A
Name Slicer_Policy_Type: #N/A
Name Slicer_Years__Policy_Start_Date: #N/A

Sheet Customer Information
A1: Customer ID | B1: Name | C1: Gender | D1: Age | E1: Age Bucket | F1: Occupation | G1: Marital Status | H1: Address (City, State, Zip Code) | I1: Policy ID
A2: CUST87425473 | B2: Norma Fisher | C2: Female | D2: 63 | E2: {=_xlfn.IFS(D2<18,"Below 18",D2<=25,"18-25",D2<=35,"26-35",D2<=45,"36-45",D2<=55,"46-55",TRUE,"56+")} -> 56+ | F2: Futures trader | G2: Married | H2: Sullivanport, New Mexico, 47431 | I2: =_xlfn.XLOOKUP('Customer Information'!$A2,'Policy Details'!$I$2:$I$5001,'Policy Details'!$A$2:$A$5001) -> POL10637039
A3: CUST52762998 | B3: Susan Wagner | C3: Male | D3: 57 | E3: {=_xlfn.IFS(D3<18,"Below 18",D3<=25,"18-25",D3<=35,"26-35",D3<=45,"36-45",D3<=55,"46-55",TRUE,"56+")} -> 56+ | F3: Herbalist | G3: Single | H3: Port Cody, Kentucky, 70305 | I3: =_xlfn.XLOOKUP('Customer Information'!$A3,'Policy Details'!$I$2:$I$5001,'Policy Details'!$A$2:$A$5001) -> POL30067784
A4: CUST78641469 | B4: Dr. Stephanie Collins | C4: Other | D4: 79 | E4: {=_xlfn.IFS(D4<18,"Below 18",D4<=25,"18-25",D4<=35,"26-35",D4<=45,"36-45",D4<=55,"46-55",TRUE,"56+")} -> 56+ | F4: Buyer, retail | G4: Widowed | H4: Thomasville, Minnesota, 57408 | I4: =_xlfn.XLOOKUP('Customer Information'!$A4,'Policy Details'!$I$2:$I$5001,'Policy Details'!$A$2:$A$5001) -> #N/A
A5: CUST82850738 | B5: Martin Harris | C5: Other | D5: 18 | E5: {=_xlfn.IFS(D5<18,"Below 18",D5<=25,"18-25",D5<=35,"26-35",D5<=45,"36-45",D5<=55,"46-55",TRUE,"56+")} -> 18-25 | F5: Sub | G5: Widowed | H5: Ramoshaven, Kentucky, 08664 | I5: =_xlfn.XLOOKUP('Customer Information'!$A5,'Policy Details'!$I$2:$I$5001,'Policy Details'!$A$2:$A$5001) -> POL32316303
A6: CUST83770928 | B6: Kimberly Smith | C6: Male | D6: 75 | E6: {=_xlfn.IFS(D6<18,"Below 18",D6<=25,"18-25",D6<=35,"26-35",D6<=45,"36-45",D6<=55,"46-55",TRUE,"56+")} -> 56+ | F6: Oceanographer | G6: Single | H6: New Tristanmouth, Kansas, 96220 | I6: =_xlfn.XLOOKUP('Customer Information'!$A6,'Policy Details'!$I$2:$I$5001,'Policy Details'!$A$2:$A$5001) -> POL60672344
A7: CUST03591575 | B7: Seth Lee | C7: Other | D7: 44 | E7: {=_xlfn.IFS(D7<18,"Below 18",D7<=25,"18-25",D7<=35,"26-35",D7<=45,"36-45",D7<=55,"46-55",TRUE,"56+")} -> 36-45 | F7: Tax inspector | G7: Divorced | H7: East Linda, Georgia, 71671 | I7: =_xlfn.XLOOKUP('Customer Information'!$A7,'Policy Details'!$I$2:$I$5001,'Policy Details'!$A$2:$A$5001) -> POL25630495
A8: CUST45352116 | B8: Bobby Flores | C8: Other | D8: 51 | E8: {=_xlfn.IFS(D8<18,"Below 18",D8<=25,"18-25",D8<=35,"26-35",D8<=45,"36-45",D8<=55,"46-55",TRUE,"56+")} -> 46-55 | F8: Rural practice surveyor | G8: Widowed | H8: Rodriguezside, Maine, 93111 | I8: =_xlfn.XLOOKUP('Customer Information'!$A8,'Policy Details'!$I$2:$I$5001,'Policy Details'!$A$2:$A$5001) -> POL02911863
A9: CUST06110068 | B9: Gary Nielsen | C9: Other | D9: 68 | E9: {=_xlfn.IFS(D9<18,"Below 18",D9<=25,"18-25",D9<=35,"26-35",D9<=45,"36-45",D9<=55,"46-55",TRUE,"56+")} -> 56+ | F9: Engineer, electronics | G9: Divorced | H9: Seanfurt, Massachusetts, 75952 | I9: =_xlfn.XLOOKUP('Customer Information'!$A9,'Policy Details'!$I$2:$I$5001,'Policy Details'!$A$2:$A$5001) -> #N/A
A10: CUST52268424 | B10: Clinton Underwood | C10: Other | D10: 63 | E10: {=_xlfn.IFS(D10<18,"Below 18",D10<=25,"18-25",D10<=35,"26-35",D10<=45,"36-45",D10<=55,"46-55",TRUE,"56+")} -> 56+ | F10: Amenity horticulturist | G10: Single | H10: Thomasland, Utah, 99801 | I10: =_xlfn.XLOOKUP('Customer Information'!$A10,'Policy Details'!$I$2:$I$5001,'Policy Details'!$A$2:$A$5001) -> #N/A
A11: CUST31531027 | B11: Chase Johnson | C11: Female | D11: 39 | E11: {=_xlfn.IFS(D11<18,"Below 18",D11<=25,"18-25",D11<=35,"26-35",D11<=45,"36-45",D11<=55,"46-55",TRUE,"56+")} -> 36-45 | F11: Catering manager | G11: Divorced | H11: Masseyhaven, Louisiana, 68893 | I11: =_xlfn.XLOOKUP('Customer Information'!$A11,'Policy Details'!$I$2:$I$5001,'Policy Details'!$A$2:$A$5001) -> #N/A
A12: CUST40782869 | B12: Sarah Jacobson | C12: Other | D12: 27 | E12: {=_xlfn.IFS(D12<18,"Below 18",D12<=25,"18-25",D12<=35,"26-35",D12<=45,"36-45",D12<=55,"46-55",TRUE,"56+")} -> 26-35 | F12: Theme park manager | G12: Single | H12: Rileymouth, New York, 87040 | I12: =_xlfn.XLOOKUP('Customer Information'!$A12,'Policy Details'!$I$2:$I$5001,'Policy Details'!$A$2:$A$5001) -> #N/A
A13: CUST11810816 | B13: Melody Haas | C13: Male | D13: 41 | E13: {=_xlfn.IFS(D13<18,"Below 18",D13<=25,"18-25",D13<=35,"26-35",D13<=45,"36-45",D13<=55,"46-55",TRUE,"56+")} -> 36-45 | F13: Marketing executive | G13: Single | H13: West Chloefort, Pennsylvania, 83095 | I13: =_xlfn.XLOOKUP('Customer Information'!$A13,'Policy Details'!$I$2:$I$5001,'Policy Details'!$A$2:$A$5001) -> #N/A
... A5001: CUST37983734 | B5001: Kevin Gonzalez | C5001: Female | D5001: 27 | E5001: {=_xlfn.IFS(D5001<18,"Below 18",D5001<=25,"18-25",D5001<=35,"26-35",D5001<=45,"36-45",D5001<=55,"46-55",TRUE,"56+")} -> 26-35 | F5001: Meteorologist | G5001: Divorced | H5001: South Jenniferland, New Hampshire, 67912 | I5001: =_xlfn.XLOOKUP('Customer Information'!$A5001,'Policy Details'!$I$2:$I$5001,'Policy Details'!$A$2:$A$5001) -> #N/A

Sheet Policy Details
A1: Policy ID | B1: Policy Type | C1: Coverage Amount | D1: Premium Amount | E1: Policy Start Date | F1: Policy End Date | G1: Payment Frequency | H1: Status | I1: Customer ID | J1: Age Bucket | K1: Gender | L1: Year
A2: POL27806251 | B2: Property | C2: 436672 | D2: 1273.79 | E2: 43461 | F2: 45525 | G2: Monthly | H2: Lapsed | I2: CUST55344519 | J2: =_xlfn.XLOOKUP('Policy Details'!$I2,'Customer Information'!$A$2:$A$5001,'Customer Information'!$E$2:$E$5001) -> 26-35 | K2: =_xlfn.XLOOKUP('Policy Details'!$I2,'Customer Information'!$A$2:$A$5001,'Customer Information'!$C$2:$C$5001) -> Female | L2: =YEAR('Policy Details'!$E2) -> 2018 | N2: =COUNTA('Policy Details'!$A$2:$A$5001) -> 5000
A3: POL96934398 | B3: Auto | C3: 102437 | D3: 1556.75 | E3: 44442 | F3: 45506 | G3: Monthly | H3: Terminated | I3: CUST71194311 | J3: =_xlfn.XLOOKUP('Policy Details'!$I3,'Customer Information'!$A$2:$A$5001,'Customer Information'!$E$2:$E$5001) -> 36-45 | K3: =_xlfn.XLOOKUP('Policy Details'!$I3,'Customer Information'!$A$2:$A$5001,'Customer Information'!$C$2:$C$5001) -> Other | L3: =YEAR('Policy Details'!$E3) -> 2021 | N3: =_xlfn.FORMULATEXT(N2) -> =COUNTA('Policy Details'!$A$2:$A$5001)
A4: POL93505220 | B4: Auto | C4: 88101 | D4: 886.53 | E4: 43130 | F4: 46025 | G4: Monthly | H4: Lapsed | I4: CUST58699451 | J4: =_xlfn.XLOOKUP('Policy Details'!$I4,'Customer Information'!$A$2:$A$5001,'Customer Information'!$E$2:$E$5001) -> 46-55 | K4: =_xlfn.XLOOKUP('Policy Details'!$I4,'Customer Information'!$A$2:$A$5001,'Customer Information'!$C$2:$C$5001) -> Other | L4: =YEAR('Policy Details'!$E4) -> 2018
A5: POL39531025 | B5: Property | C5: 459915 | D5: 197.75 | E5: 44654 | F5: 48259 | G5: Quarterly | H5: Terminated | I5: CUST72186583 | J5: =_xlfn.XLOOKUP('Policy Details'!$I5,'Customer Information'!$A$2:$A$5001,'Customer Information'!$E$2:$E$5001) -> 26-35 | K5: =_xlfn.XLOOKUP('Policy Details'!$I5,'Customer Information'!$A$2:$A$5001,'Customer Information'!$C$2:$C$5001) -> Male | L5: =YEAR('Policy Details'!$E5) -> 2022 | N5: =COUNTA(_xlfn.UNIQUE('Policy Details'!$I$2:$I$5001)) -> 3148
A6: POL38769300 | B6: Health | C6: 22098 | D6: 868.51 | E6: 44471 | F6: 46648 | G6: Quarterly | H6: Active | I6: CUST04808502 | J6: =_xlfn.XLOOKUP('Policy Details'!$I6,'Customer Information'!$A$2:$A$5001,'Customer Information'!$E$2:$E$5001) -> 56+ | K6: =_xlfn.XLOOKUP('Policy Details'!$I6,'Customer Information'!$A$2:$A$5001,'Customer Information'!$C$2:$C$5001) -> Male | L6: =YEAR('Policy Details'!$E6) -> 2021 | N6: =_xlfn.FORMULATEXT(N5) -> =COUNTA(UNIQUE('Policy Details'!$I$2:$I$5001))
A7: POL07841878 | B7: Health | C7: 347514 | D7: 1931.83 | E7: 44091 | F7: 46262 | G7: Monthly | H7: Active | I7: CUST47527169 | J7: =_xlfn.XLOOKUP('Policy Details'!$I7,'Customer Information'!$A$2:$A$5001,'Customer Information'!$E$2:$E$5001) -> 36-45 | K7: =_xlfn.XLOOKUP('Policy Details'!$I7,'Customer Information'!$A$2:$A$5001,'Customer Information'!$C$2:$C$5001) -> Other | L7: =YEAR('Policy Details'!$E7) -> 2020
A8: POL21963992 | B8: Property | C8: 288036 | D8: 247.04 | E8: 43186 | F8: 43681 | G8: Monthly | H8: Active | I8: CUST57892719 | J8: =_xlfn.XLOOKUP('Policy Details'!$I8,'Customer Information'!$A$2:$A$5001,'Customer Information'!$E$2:$E$5001) -> 26-35 | K8: =_xlfn.XLOOKUP('Policy Details'!$I8,'Customer Information'!$A$2:$A$5001,'Customer Information'!$C$2:$C$5001) -> Female | L8: =YEAR('Policy Details'!$E8) -> 2018 | N8: =COUNTIF('Policy Details'!$H$2:$H$5001,"active") -> 1682
A9: POL64589705 | B9: Health | C9: 394231 | D9: 152.13 | E9: 45457 | F9: 45995 | G9: Quarterly | H9: Terminated | I9: CUST97231935 | J9: =_xlfn.XLOOKUP('Policy Details'!$I9,'Customer Information'!$A$2:$A$5001,'Customer Information'!$E$2:$E$5001) -> 36-45 | K9: =_xlfn.XLOOKUP('Policy Details'!$I9,'Customer Information'!$A$2:$A$5001,'Customer Information'!$C$2:$C$5001) -> Male | L9: =YEAR('Policy Details'!$E9) -> 2024 | N9: =_xlfn.FORMULATEXT(N8) -> =COUNTIF('Policy Details'!$H$2:$H$5001,"active")
A10: POL49133977 | B10: Property | C10: 148162 | D10: 1383.65 | E10: 42100 | F10: 43731 | G10: Quarterly | H10: Terminated | I10: CUST67080051 | J10: =_xlfn.XLOOKUP('Policy Details'!$I10,'Customer Information'!$A$2:$A$5001,'Customer Information'!$E$2:$E$5001) -> 56+ | K10: =_xlfn.XLOOKUP('Policy Details'!$I10,'Customer Information'!$A$2:$A$5001,'Customer Information'!$C$2:$C$5001) -> Other | L10: =YEAR('Policy Details'!$E10) -> 2015
A11: POL80278196 | B11: Life | C11: 376522 | D11: 1546.14 | E11: 44136 | F11: 46560 | G11: Quarterly | H11: Lapsed | I11: CUST45705025 | J11: =_xlfn.XLOOKUP('Policy Details'!$I11,'Customer Information'!$A$2:$A$5001,'Customer Information'!$E$2:$E$5001) -> 46-55 | K11: =_xlfn.XLOOKUP('Policy Details'!$I11,'Customer Information'!$A$2:$A$5001,'Customer Information'!$C$2:$C$5001) -> Male | L11: =YEAR('Policy Details'!$E11) -> 2020 | N11: =COUNTIF('Policy Details'!$H$2:$H$5001,"lapsed") -> 1640
A12: POL89935970 | B12: Property | C12: 499740 | D12: 1488.73 | E12: 44246 | F12: 46730 | G12: Quarterly | H12: Active | I12: CUST47003736 | J12: =_xlfn.XLOOKUP('Policy Details'!$I12,'Customer Information'!$A$2:$A$5001,'Customer Information'!$E$2:$E$5001) -> 56+ | K12: =_xlfn.XLOOKUP('Policy Details'!$I12,'Customer Information'!$A$2:$A$5001,'Customer Information'!$C$2:$C$5001) -> Male | L12: =YEAR('Policy Details'!$E12) -> 2021 | N12: =_xlfn.FORMULATEXT(N11) -> =COUNTIF('Policy Details'!$H$2:$H$5001,"lapsed")
A13: POL40425029 | B13: Life | C13: 413248 | D13: 279.96 | E13: 44415 | F13: 45463 | G13: Monthly | H13: Active | I13: CUST15756529 | J13: =_xlfn.XLOOKUP('Policy Details'!$I13,'Customer Information'!$A$2:$A$5001,'Customer Information'!$E$2:$E$5001) -> 56+ | K13: =_xlfn.XLOOKUP('Policy Details'!$I13,'Customer Information'!$A$2:$A$5001,'Customer Information'!$C$2:$C$5001) -> Other | L13: =YEAR('Policy Details'!$E13) -> 2021
A14: POL59138324 | B14: Health | C14: 274869 | D14: 288.84 | E14: 44030 | F14: 46514 | G14: Annually | H14: Lapsed | I14: CUST24464034 | J14: =_xlfn.XLOOKUP('Policy Details'!$I14,'Customer Information'!$A$2:$A$5001,'Customer Information'!$E$2:$E$5001) -> 36-45 | K14: =_xlfn.XLOOKUP('Policy Details'!$I14,'Customer Information'!$A$2:$A$5001,'Customer Information'!$C$2:$C$5001) -> Female | L14: =YEAR('Policy Details'!$E14) -> 2020 | N14: =COUNTIF('Policy Details'!$H$2:$H$5001,"terminated") -> 1678
A15: POL79312567 | B15: Auto | C15: 17245 | D15: 186.85 | E15: 45546 | F15: 49062 | G15: Annually | H15: Active | I15: CUST18926459 | J15: =_xlfn.XLOOKUP('Policy Details'!$I15,'Customer Information'!$A$2:$A$5001,'Customer Information'!$E$2:$E$5001) -> 56+ | K15: =_xlfn.XLOOKUP('Policy Details'!$I15,'Customer Information'!$A$2:$A$5001,'Customer Information'!$C$2:$C$5001) -> Female | L15: =YEAR('Policy Details'!$E15) -> 2024 | N15: =_xlfn.FORMULATEXT(N14) -> =COUNTIF('Policy Details'!$H$2:$H$5001,"terminated")
A16: POL05760636 | B16: Life | C16: 86153 | D16: 1863.95 | E16: 45567 | F16: 46672 | G16: Annually | H16: Active | I16: CUST92370305 | J16: =_xlfn.XLOOKUP('Policy Details'!$I16,'Customer Information'!$A$2:$A$5001,'Customer Information'!$E$2:$E$5001) -> 18-25 | K16: =_xlfn.XLOOKUP('Policy Details'!$I16,'Customer Information'!$A$2:$A$5001,'Customer Information'!$C$2:$C$5001) -> Female | L16: =YEAR('Policy Details'!$E16) -> 2024
A17: POL09606287 | B17: Life | C17: 430745 | D17: 722.68 | E17: 45295 | F17: 45990 | G17: Monthly | H17: Terminated | I17: CUST93527354 | J17: =_xlfn.XLOOKUP('Policy Details'!$I17,'Customer Information'!$A$2:$A$5001,'Customer Information'!$E$2:$E$5001) -> 26-35 | K17: =_xlfn.XLOOKUP('Policy Details'!$I17,'Customer Information'!$A$2:$A$5001,'Customer Information'!$C$2:$C$5001) -> Female | L17: =YEAR('Policy Details'!$E17) -> 2024 | N17: {=COUNTIF('Policy Details'!$H$2:$H$5001,{"active","lapsed","terminated"})} -> 1682 | O17: 1640 | P17: 1678
A18: POL70474651 | B18: Health | C18: 327028 | D18: 962.68 | E18: 45235 | F18: 47622 | G18: Monthly | H18: Lapsed | I18: CUST54507478 | J18: =_xlfn.XLOOKUP('Policy Details'!$I18,'Customer Information'!$A$2:$A$5001,'Customer Information'!$E$2:$E$5001) -> 56+ | K18: =_xlfn.XLOOKUP('Policy Details'!$I18,'Customer Information'!$A$2:$A$5001,'Customer Information'!$C$2:$C$5001) -> Other | L18: =YEAR('Policy Details'!$E18) -> 2023
A19: POL89907664 | B19: Life | C19: 74169 | D19: 492.23 | E19: 44624 | F19: 47127 | G19: Monthly | H19: Terminated | I19: CUST00235004 | J19: =_xlfn.XLOOKUP('Policy Details'!$I19,'Customer Information'!$A$2:$A$5001,'Customer Information'!$E$2:$E$5001) -> 56+ | K19: =_xlfn.XLOOKUP('Policy Details'!$I19,'Customer Information'!$A$2:$A$5001,'Customer Information'!$C$2:$C$5001) -> Other | L19: =YEAR('Policy Details'!$E19) -> 2022 | N19: =N8/N2 -> 0.3364 | O19: =N11/N2 -> 0.328 | P19: =N14/N2 -> 0.3356
A20: POL64943722 | B20: Health | C20: 221353 | D20: 824.14 | E20: 45283 | F20: 47600 | G20: Annually | H20: Terminated | I20: CUST54318231 | J20: =_xlfn.XLOOKUP('Policy Details'!$I20,'Customer Information'!$A$2:$A$5001,'Customer Information'!$E$2:$E$5001) -> 18-25 | K20: =_xlfn.XLOOKUP('Policy Details'!$I20,'Customer Information'!$A$2:$A$5001,'Customer Information'!$C$2:$C$5001) -> Female | L20: =YEAR('Policy Details'!$E20) -> 2023 | N20: Active | O20: Lapsed | P20: Terminated
A21: POL90960707 | B21: Health | C21: 276513 | D21: 890.01 | E21: 44883 | F21: 45913 | G21: Annually | H21: Active | I21: CUST65008360 | J21: =_xlfn.XLOOKUP('Policy Details'!$I21,'Customer Information'!$A$2:$A$5001,'Customer Information'!$E$2:$E$5001) -> 18-25 | K21: =_xlfn.XLOOKUP('Policy Details'!$I21,'Customer Information'!$A$2:$A$5001,'Customer Information'!$C$2:$C$5001) -> Female | L21: =YEAR('Policy Details'!$E21) -> 2022
A22: POL59179996 | B22: Property | C22: 209276 | D22: 315.72 | E22: 43135 | F22: 45756 | G22: Monthly | H22: Active | I22: CUST18337391 | J22: =_xlfn.XLOOKUP('Policy Details'!$I22,'Customer Information'!$A$2:$A$5001,'Customer Information'!$E$2:$E$5001) -> 46-55 | K22: =_xlfn.XLOOKUP('Policy Details'!$I22,'Customer Information'!$A$2:$A$5001,'Customer Information'!$C$2:$C$5001) -> Male | L22: =YEAR('Policy Details'!$E22) -> 2018
A23: POL24718635 | B23: Property | C23: 284606 | D23: 730.56 | E23: 44769 | F23: 46734 | G23: Annually | H23: Active | I23: CUST94024764 | J23: =_xlfn.XLOOKUP('Policy Details'!$I23,'Customer Information'!$A$2:$A$5001,'Customer Information'!$E$2:$E$5001) -> 56+ | K23: =_xlfn.XLOOKUP('Policy Details'!$I23,'Customer Information'!$A$2:$A$5001,'Customer Information'!$C$2:$C$5001) -> Other | L23: =YEAR('Policy Details'!$E23) -> 2022
A24: POL19704549 | B24: Property | C24: 107142 | D24: 872.55 | E24: 43322 | F24: 45811 | G24: Quarterly | H24: Lapsed | I24: CUST37162794 | J24: =_xlfn.XLOOKUP('Policy Details'!$I24,'Customer Information'!$A$2:$A$5001,'Customer Information'!$E$2:$E$5001) -> 56+ | K24: =_xlfn.XLOOKUP('Policy Details'!$I24,'Customer Information'!$A$2:$A$5001,'Customer Information'!$C$2:$C$5001) -> Other | L24: =YEAR('Policy Details'!$E24) -> 2018
A25: POL99720690 | B25: Life | C25: 43579 | D25: 981.71 | E25: 42112 | F25: 45124 | G25: Monthly | H25: Active | I25: CUST80574300 | J25: =_xlfn.XLOOKUP('Policy Details'!$I25,'Customer Information'!$A$2:$A$5001,'Customer Information'!$E$2:$E$5001) -> 56+ | K25: =_xlfn.XLOOKUP('Policy Details'!$I25,'Customer Information'!$A$2:$A$5001,'Customer Information'!$C$2:$C$5001) -> Female | L25: =YEAR('Policy Details'!$E25) -> 2015
A26: POL07613630 | B26: Health | C26: 103548 | D26: 1927.96 | E26: 43499 | F26: 46229 | G26: Monthly | H26: Active | I26: CUST53450793 | J26: =_xlfn.XLOOKUP('Policy Details'!$I26,'Customer Information'!$A$2:$A$5001,'Customer Information'!$E$2:$E$5001) -> 36-45 | K26: =_xlfn.XLOOKUP('Policy Details'!$I26,'Customer Information'!$A$2:$A$5001,'Customer Information'!$C$2:$C$5001) -> Male | L26: =YEAR('Policy Details'!$E26) -> 2019
A27: POL68368522 | B27: Health | C27: 467228 | D27: 1359.2 | E27: 43786 | F27: 45904 | G27: Annually | H27: Lapsed | I27: CUST00957425 | J27: =_xlfn.XLOOKUP('Policy Details'!$I27,'Customer Information'!$A$2:$A$5001,'Customer Information'!$E$2:$E$5001) -> 26-35 | K27: =_xlfn.XLOOKUP('Policy Details'!$I27,'Customer Information'!$A$2:$A$5001,'Customer Information'!$C$2:$C$5001) -> Other | L27: =YEAR('Policy Details'!$E27) -> 2019
A28: POL96166579 | B28: Life | C28: 132969 | D28: 1666.16 | E28: 42829 | F28: 45596 | G28: Monthly | H28: Terminated | I28: CUST78371218 | J28: =_xlfn.XLOOKUP('Policy Details'!$I28,'Customer Information'!$A$2:$A$5001,'Customer Information'!$E$2:$E$5001) -> 36-45 | K28: =_xlfn.XLOOKUP('Policy Details'!$I28,'Customer Information'!$A$2:$A$5001,'Customer Information'!$C$2:$C$5001) -> Female | L28: =YEAR('Policy Details'!$E28) -> 2017
A29: POL78863924 | B29: Health | C29: 192018 | D29: 1528.72 | E29: 44097 | F29: 45259 | G29: Monthly | H29: Lapsed | I29: CUST36691624 | J29: =_xlfn.XLOOKUP('Policy Details'!$I29,'Customer Information'!$A$2:$A$5001,'Customer Information'!$E$2:$E$5001) -> 46-55 | K29: =_xlfn.XLOOKUP('Policy Details'!$I29,'Customer Information'!$A$2:$A$5001,'Customer Information'!$C$2:$C$5001) -> Male | L29: =YEAR('Policy Details'!$E29) -> 2020
A30: POL66542527 | B30: Life | C30: 209098 | D30: 1670.55 | E30: 43608 | F30: 45412 | G30: Quarterly | H30: Active | I30: CUST09670639 | J30: =_xlfn.XLOOKUP('Policy Details'!$I30,'Customer Information'!$A$2:$A$5001,'Customer Information'!$E$2:$E$5001) -> 56+ | K30: =_xlfn.XLOOKUP('Policy Details'!$I30,'Customer Information'!$A$2:$A$5001,'Customer Information'!$C$2:$C$5001) -> Female | L30: =YEAR('Policy Details'!$E30) -> 2019
A31: POL21617511 | B31: Health | C31: 302289 | D31: 748.41 | E31: 43950 | F31: 46892 | G31: Quarterly | H31: Terminated | I31: CUST23186598 | J31: =_xlfn.XLOOKUP('Policy Details'!$I31,'Customer Information'!$A$2:$A$5001,'Customer Information'!$E$2:$E$5001) -> 36-45 | K31: =_xlfn.XLOOKUP('Policy Details'!$I31,'Customer Information'!$A$2:$A$5001,'Customer Information'!$C$2:$C$5001) -> Male | L31: =YEAR('Policy Details'!$E31) -> 2020
A32: POL96023706 | B32: Life | C32: 312505 | D32: 1031.19 | E32: 43825 | F32: 47112 | G32: Annually | H32: Active | I32: CUST47187133 | J32: =_xlfn.XLOOKUP('Policy Details'!$I32,'Customer Information'!$A$2:$A$5001,'Customer Information'!$E$2:$E$5001) -> 36-45 | K32: =_xlfn.XLOOKUP('Policy Details'!$I32,'Customer Information'!$A$2:$A$5001,'Customer Information'!$C$2:$C$5001) -> Male | L32: =YEAR('Policy Details'!$E32) -> 2019
... A5001: POL16711858 | B5001: Property | C5001: 343604 | D5001: 393.1 | E5001: 44534 | F5001: 47830 | G5001: Monthly | H5001: Terminated | I5001: CUST90434699 | J5001: =_xlfn.XLOOKUP('Policy Details'!$I5001,'Customer Information'!$A$2:$A$5001,'Customer Information'!$E$2:$E$5001) -> 46-55 | K5001: =_xlfn.XLOOKUP('Policy Details'!$I5001,'Customer Information'!$A$2:$A$5001,'Customer Information'!$C$2:$C$5001) -> Male | L5001: =YEAR('Policy Details'!$E5001) -> 2021

Sheet Claims
A1: Claim ID | B1: Date of Claim | C1: Claim Amount | D1: Claim Status | E1: Reason for Claim | F1: Settlement Date | G1: Policy ID | H1: Policy Type
A2: CLM77924411 | B2: 45505 | C2: 54655 | D2: Approved | E2: Song member cover lose effect wall walk. | F2: 45516 | G2: POL56612277 | H2: =_xlfn.XLOOKUP(Claims!$G2,Table1[Policy ID],Table1[Policy Type]) -> Auto | J2: =SUM(Claims!$C$2:$C$5001) -> 251378846
A3: CLM28779034 | B3: 45295 | C3: 94225 | D3: Pending | E3: Mean model toward might main maintain. | F3: 45339 | G3: POL69932027 | H3: =_xlfn.XLOOKUP(Claims!$G3,Table1[Policy ID],Table1[Policy Type]) -> Life
A4: CLM42025979 | B4: 45381 | C4: 17652 | D4: Approved | E4: Day outside produce easy. | G4: POL42688275 | H4: =_xlfn.XLOOKUP(Claims!$G4,Table1[Policy ID],Table1[Policy Type]) -> Auto
A5: CLM69566101 | B5: 44930 | C5: 69929 | D5: Approved | E5: Start after receive daughter newspaper change. | F5: 44981 | G5: POL66279716 | H5: =_xlfn.XLOOKUP(Claims!$G5,Table1[Policy ID],Table1[Policy Type]) -> Health
A6: CLM58620367 | B6: 44764 | C6: 96366 | D6: Approved | E6: Policy yet yes improve draw some. | G6: POL77439955 | H6: =_xlfn.XLOOKUP(Claims!$G6,Table1[Policy ID],Table1[Policy Type]) -> Property
A7: CLM07454489 | B7: 44014 | C7: 63905 | D7: Denied | E7: Success move worker among. | F7: 44065 | G7: POL64965934 | H7: =_xlfn.XLOOKUP(Claims!$G7,Table1[Policy ID],Table1[Policy Type]) -> Life
A8: CLM27552701 | B8: 44592 | C8: 61121 | D8: Pending | E8: Professor four degree feeling person author cell. | F8: 44610 | G8: POL73019543 | H8: =_xlfn.XLOOKUP(Claims!$G8,Table1[Policy ID],Table1[Policy Type]) -> Life
A9: CLM77756278 | B9: 44795 | C9: 12547 | D9: Pending | E9: Science own thing from class senior provide. | F9: 44837 | G9: POL19552952 | H9: =_xlfn.XLOOKUP(Claims!$G9,Table1[Policy ID],Table1[Policy Type]) -> Health
A10: CLM05146130 | B10: 44162 | C10: 57203 | D10: Denied | E10: Together mouth various child cultural. | G10: POL07805552 | H10: =_xlfn.XLOOKUP(Claims!$G10,Table1[Policy ID],Table1[Policy Type]) -> Health
A11: CLM19272700 | B11: 44084 | C11: 62916 | D11: Approved | E11: Both remain note instead first probably. | F11: 44145 | G11: POL88177917 | H11: =_xlfn.XLOOKUP(Claims!$G11,Table1[Policy ID],Table1[Policy Type]) -> Health
A12: CLM85060604 | B12: 44289 | C12: 79536 | D12: Denied | E12: Company raise drive. | F12: 44304 | G12: POL71221796 | H12: =_xlfn.XLOOKUP(Claims!$G12,Table1[Policy ID],Table1[Policy Type]) -> Property
A13: CLM86056395 | B13: 44930 | C13: 21469 | D13: Denied | E13: Church option sometimes pick their arm century. | F13: 45001 | G13: POL61467343 | H13: =_xlfn.XLOOKUP(Claims!$G13,Table1[Policy ID],Table1[Policy Type]) -> Health
A14: CLM98463712 | B14: 44903 | C14: 65329 | D14: Denied | E14: Shake age official become season. | F14: 44928 | G14: POL62363777 | H14: =_xlfn.XLOOKUP(Claims!$G14,Table1[Policy ID],Table1[Policy Type]) -> Property
A15: CLM98579912 | B15: 45446 | C15: 80670 | D15: Pending | E15: Seek political threat about join determine. | F15: 45467 | G15: POL50374708 | H15: =_xlfn.XLOOKUP(Claims!$G15,Table1[Policy ID],Table1[Policy Type]) -> Health
A16: CLM90637957 | B16: 44216 | C16: 45282 | D16: Pending | E16: Network bit someone strong mention. | F16: 44271 | G16: POL88242759 | H16: =_xlfn.XLOOKUP(Claims!$G16,Table1[Policy ID],Table1[Policy Type]) -> Health
A17: CLM12125464 | B17: 45325 | C17: 50353 | D17: Denied | E17: Window above operation perhaps teach east world bit. | F17: 45343 | G17: POL27437608 | H17: =_xlfn.XLOOKUP(Claims!$G17,Table1[Policy ID],Table1[Policy Type]) -> Health
A18: CLM45720439 | B18: 45049 | C18: 39427 | D18: Denied | E18: Scientist account cover central song. | F18: 45111 | G18: POL77019254 | H18: =_xlfn.XLOOKUP(Claims!$G18,Table1[Policy ID],Table1[Policy Type]) -> Auto
A19: CLM50141230 | B19: 44554 | C19: 43102 | D19: Pending | E19: Always crime indeed idea back. | G19: POL72656147 | H19: =_xlfn.XLOOKUP(Claims!$G19,Table1[Policy ID],Table1[Policy Type]) -> Health
A20: CLM97150673 | B20: 45523 | C20: 35473 | D20: Pending | E20: Center without look hundred difference writer most. | F20: 45553 | G20: POL19255943 | H20: =_xlfn.XLOOKUP(Claims!$G20,Table1[Policy ID],Table1[Policy Type]) -> Auto
A21: CLM51837945 | B21: 44691 | C21: 13146 | D21: Approved | E21: While operation interview determine let movement. | F21: 44740 | G21: POL85518381 | H21: =_xlfn.XLOOKUP(Claims!$G21,Table1[Policy ID],Table1[Policy Type]) -> Life
A22: CLM82967170 | B22: 44637 | C22: 2324 | D22: Pending | E22: Option mean marriage news wait major. | F22: 44657 | G22: POL32845970 | H22: =_xlfn.XLOOKUP(Claims!$G22,Table1[Policy ID],Table1[Policy Type]) -> Property
A23: CLM62837956 | B23: 43959 | C23: 36126 | D23: Denied | E23: Agent several by century quality dream above. | G23: POL95370014 | H23: =_xlfn.XLOOKUP(Claims!$G23,Table1[Policy ID],Table1[Policy Type]) -> Property
A24: CLM53724406 | B24: 43851 | C24: 80226 | D24: Approved | E24: Director benefit movie want increase shake stage. | G24: POL45794212 | H24: =_xlfn.XLOOKUP(Claims!$G24,Table1[Policy ID],Table1[Policy Type]) -> Life
A25: CLM16412694 | B25: 44910 | C25: 32102 | D25: Approved | E25: Nothing body who stand. | F25: 44971 | G25: POL61653642 | H25: =_xlfn.XLOOKUP(Claims!$G25,Table1[Policy ID],Table1[Policy Type]) -> Auto
A26: CLM51625573 | B26: 45276 | C26: 31862 | D26: Pending | E26: Only bill later huge. | F26: 45304 | G26: POL93167566 | H26: =_xlfn.XLOOKUP(Claims!$G26,Table1[Policy ID],Table1[Policy Type]) -> Property
A27: CLM51036457 | B27: 45089 | C27: 25719 | D27: Denied | E27: Water reduce shoulder technology knowledge discussion network then. | F27: 45143 | G27: POL67872849 | H27: =_xlfn.XLOOKUP(Claims!$G27,Table1[Policy ID],Table1[Policy Type]) -> Property
A28: CLM04762722 | B28: 44060 | C28: 3571 | D28: Approved | E28: Accept billion sure peace hold meeting. | F28: 44079 | G28: POL61884063 | H28: =_xlfn.XLOOKUP(Claims!$G28,Table1[Policy ID],Table1[Policy Type]) -> Property
A29: CLM43338826 | B29: 45440 | C29: 80190 | D29: Denied | E29: Myself none late. | F29: 45483 | G29: POL89077589 | H29: =_xlfn.XLOOKUP(Claims!$G29,Table1[Policy ID],Table1[Policy Type]) -> Life
A30: CLM66194342 | B30: 44935 | C30: 56151 | D30: Denied | E30: Bill few morning executive old. | F30: 45021 | G30: POL23806593 | H30: =_xlfn.XLOOKUP(Claims!$G30,Table1[Policy ID],Table1[Policy Type]) -> Auto
A31: CLM27235742 | B31: 44191 | C31: 83640 | D31: Denied | E31: Act new real know live. | G31: POL29474046 | H31: =_xlfn.XLOOKUP(Claims!$G31,Table1[Policy ID],Table1[Policy Type]) -> Auto
A32: CLM02888122 | B32: 44028 | C32: 9836 | D32: Pending | E32: Rule special Democrat million. | F32: 44060 | G32: POL96504333 | H32: =_xlfn.XLOOKUP(Claims!$G32,Table1[Policy ID],Table1[Policy Type]) -> Auto
A33: CLM23673303 | B33: 43839 | C33: 22275 | D33: Pending | E33: Send ok soldier end. | F33: 43902 | G33: POL81591533 | H33: =_xlfn.XLOOKUP(Claims!$G33,Table1[Policy ID],Table1[Policy Type]) -> Property
A34: CLM98491523 | B34: 45301 | C34: 77913 | D34: Approved | E34: Month station thing police level. | F34: 45318 | G34: POL01681251 | H34: =_xlfn.XLOOKUP(Claims!$G34,Table1[Policy ID],Table1[Policy Type]) -> Auto
A35: CLM20286630 | B35: 44269 | C35: 39165 | D35: Denied | E35: According plan week peace officer particularly. | G35: POL13181377 | H35: =_xlfn.XLOOKUP(Claims!$G35,Table1[Policy ID],Table1[Policy Type]) -> Life
A36: CLM66676001 | B36: 44530 | C36: 90112 | D36: Approved | E36: Anyone national speak protect professor process station. | F36: 44565 | G36: POL43969785 | H36: =_xlfn.XLOOKUP(Claims!$G36,Table1[Policy ID],Table1[Policy Type]) -> Auto
A37: CLM16206090 | B37: 44045 | C37: 18632 | D37: Denied | E37: Indeed particular keep feeling allow individual. | G37: POL34180846 | H37: =_xlfn.XLOOKUP(Claims!$G37,Table1[Policy ID],Table1[Policy Type]) -> Property
A38: CLM93705007 | B38: 45132 | C38: 35200 | D38: Approved | E38: Again evidence yourself somebody light already. | F38: 45182 | G38: POL21441518 | H38: =_xlfn.XLOOKUP(Claims!$G38,Table1[Policy ID],Table1[Policy Type]) -> Auto
A39: CLM86984670 | B39: 44514 | C39: 31749 | D39: Denied | E39: Eat among change goal. | F39: 44524 | G39: POL64544270 | H39: =_xlfn.XLOOKUP(Claims!$G39,Table1[Policy ID],Table1[Policy Type]) -> Property
A40: CLM90814794 | B40: 45359 | C40: 7435 | D40: Denied | E40: Great near boy success. | F40: 45420 | G40: POL54561530 | H40: =_xlfn.XLOOKUP(Claims!$G40,Table1[Policy ID],Table1[Policy Type]) -> Auto
A41: CLM55030421 | B41: 45257 | C41: 76501 | D41: Pending | E41: Education themselves see letter remember unit director. | F41: 45329 | G41: POL95768809 | H41: =_xlfn.XLOOKUP(Claims!$G41,Table1[Policy ID],Table1[Policy Type]) -> Auto
A42: CLM38868037 | B42: 44079 | C42: 90208 | D42: Pending | E42: American material style through evidence southern deep. | G42: POL96685286 | H42: =_xlfn.XLOOKUP(Claims!$G42,Table1[Policy ID],Table1[Policy Type]) -> Property
A43: CLM09669839 | B43: 44210 | C43: 84492 | D43: Denied | E43: Sign human long air already federal peace art. | F43: 44291 | G43: POL82401042 | H43: =_xlfn.XLOOKUP(Claims!$G43,Table1[Policy ID],Table1[Policy Type]) -> Auto
A44: CLM18327776 | B44: 43834 | C44: 51746 | D44: Approved | E44: Find where back sea program fear. | F44: 43856 | G44: POL03461173 | H44: =_xlfn.XLOOKUP(Claims!$G44,Table1[Policy ID],Table1[Policy Type]) -> Life
A45: CLM60097748 | B45: 44505 | C45: 21838 | D45: Pending | E45: Deal service agent already improve style. | F45: 44577 | G45: POL59179996 | H45: =_xlfn.XLOOKUP(Claims!$G45,Table1[Policy ID],Table1[Policy Type]) -> Property
A46: CLM57112717 | B46: 44502 | C46: 28629 | D46: Approved | E46: Two second say if tough voice. | G46: POL23145476 | H46: =_xlfn.XLOOKUP(Claims!$G46,Table1[Policy ID],Table1[Policy Type]) -> Health
A47: CLM65938667 | B47: 45140 | C47: 80531 | D47: Denied | E47: Movie so writer price rise tell old. | F47: 45152 | G47: POL82016751 | H47: =_xlfn.XLOOKUP(Claims!$G47,Table1[Policy ID],Table1[Policy Type]) -> Health
A48: CLM14071810 | B48: 44822 | C48: 73972 | D48: Pending | E48: Head mission number natural model. | F48: 44895 | G48: POL09137788 | H48: =_xlfn.XLOOKUP(Claims!$G48,Table1[Policy ID],Table1[Policy Type]) -> Life
A49: CLM56509285 | B49: 44878 | C49: 53398 | D49: Pending | E49: Crime speak fill step. | F49: 44907 | G49: POL70419372 | H49: =_xlfn.XLOOKUP(Claims!$G49,Table1[Policy ID],Table1[Policy Type]) -> Health
A50: CLM11001484 | B50: 44284 | C50: 62327 | D50: Denied | E50: Group top woman everyone quickly question majority. | G50: POL90801398 | H50: =_xlfn.XLOOKUP(Claims!$G50,Table1[Policy ID],Table1[Policy Type]) -> Health
A51: CLM65918046 | B51: 44101 | C51: 30879 | D51: Pending | E51: Doctor especially today value become term identify. | G51: POL82791377 | H51: =_xlfn.XLOOKUP(Claims!$G51,Table1[Policy ID],Table1[Policy Type]) -> Health
A52: CLM81536271 | B52: 44811 | C52: 18231 | D52: Pending | E52: Year else front than choice. | F52: 44862 | G52: POL15877374 | H52: =_xlfn.XLOOKUP(Claims!$G52,Table1[Policy ID],Table1[Policy Type]) -> Life
A53: CLM14776484 | B53: 45080 | C53: 33327 | D53: Approved | E53: Why alone its open upon. | G53: POL59779212 | H53: =_xlfn.XLOOKUP(Claims!$G53,Table1[Policy ID],Table1[Policy Type]) -> Life
A54: CLM33580673 | B54: 45046 | C54: 89459 | D54: Denied | E54: Both series shoulder specific offer language traditional. | G54: POL07342539 | H54: =_xlfn.XLOOKUP(Claims!$G54,Table1[Policy ID],Table1[Policy Type]) -> Health
A55: CLM37236202 | B55: 45519 | C55: 10248 | D55: Denied | E55: Staff next movie page drop. | F55: 45562 | G55: POL41037493 | H55: =_xlfn.XLOOKUP(Claims!$G55,Table1[Policy ID],Table1[Policy Type]) -> Health
A56: CLM51134239 | B56: 45026 | C56: 86284 | D56: Pending | E56: Fast team dark century strategy hit. | F56: 45077 | G56: POL82137065 | H56: =_xlfn.XLOOKUP(Claims!$G56,Table1[Policy ID],Table1[Policy Type]) -> Health
A57: CLM36331542 | B57: 45627 | C57: 47685 | D57: Pending | E57: Seek send believe western chair usually. | G57: POL90934498 | H57: =_xlfn.XLOOKUP(Claims!$G57,Table1[Policy ID],Table1[Policy Type]) -> Auto
A58: CLM68935390 | B58: 44384 | C58: 4745 | D58: Approved | E58: Gas black evidence. | G58: POL83133699 | H58: =_xlfn.XLOOKUP(Claims!$G58,Table1[Policy ID],Table1[Policy Type]) -> Life
A59: CLM05192558 | B59: 44970 | C59: 64302 | D59: Approved | E59: Own would fire. | G59: POL01761052 | H59: =_xlfn.XLOOKUP(Claims!$G59,Table1[Policy ID],Table1[Policy Type]) -> Life
A60: CLM34252551 | B60: 44122 | C60: 48742 | D60: Approved | E60: Give computer keep form research despite. | G60: POL08643765 | H60: =_xlfn.XLOOKUP(Claims!$G60,Table1[Policy ID],Table1[Policy Type]) -> Property
A61: CLM82206005 | B61: 44416 | C61: 48335 | D61: Pending | E61: Adult conference safe poor its industry coach. | G61: POL25617891 | H61: =_xlfn.XLOOKUP(Claims!$G61,Table1[Policy ID],Table1[Policy Type]) -> Auto
A62: CLM25855066 | B62: 44443 | C62: 78981 | D62: Pending | E62: Economy whose same miss national. | F62: 44496 | G62: POL08689656 | H62: =_xlfn.XLOOKUP(Claims!$G62,Table1[Policy ID],Table1[Policy Type]) -> Health
A63: CLM66661573 | B63: 44892 | C63: 85396 | D63: Denied | E63: Simply charge partner poor with. | F63: 44972 | G63: POL64120254 | H63: =_xlfn.XLOOKUP(Claims!$G63,Table1[Policy ID],Table1[Policy Type]) -> Auto
A64: CLM79682557 | B64: 44739 | C64: 91925 | D64: Denied | E64: Often bring five. | F64: 44803 | G64: POL45114954 | H64: =_xlfn.XLOOKUP(Claims!$G64,Table1[Policy ID],Table1[Policy Type]) -> Auto
A65: CLM70589989 | B65: 44640 | C65: 38297 | D65: Approved | E65: Wonder piece wait look true no remember if. | F65: 44727 | G65: POL63517748 | H65: =_xlfn.XLOOKUP(Claims!$G65,Table1[Policy ID],Table1[Policy Type]) -> Life
A66: CLM31815501 | B66: 44668 | C66: 66148 | D66: Pending | E66: Several produce class customer alone. | F66: 44748 | G66: POL91259489 | H66: =_xlfn.XLOOKUP(Claims!$G66,Table1[Policy ID],Table1[Policy Type]) -> Property
A67: CLM63185712 | B67: 44533 | C67: 12659 | D67: Approved | E67: Former table finish boy single practice. | F67: 44586 | G67: POL39463277 | H67: =_xlfn.XLOOKUP(Claims!$G67,Table1[Policy ID],Table1[Policy Type]) -> Property
A68: CLM23146150 | B68: 45283 | C68: 65025 | D68: Pending | E68: Education shoulder hand father production order choice. | F68: 45310 | G68: POL75706298 | H68: =_xlfn.XLOOKUP(Claims!$G68,Table1[Policy ID],Table1[Policy Type]) -> Property
A69: CLM01553708 | B69: 45470 | C69: 66661 | D69: Approved | E69: Sound be certainly fly picture space. | F69: 45495 | G69: POL33049382 | H69: =_xlfn.XLOOKUP(Claims!$G69,Table1[Policy ID],Table1[Policy Type]) -> Life
A70: CLM66074257 | B70: 45636 | C70: 7273 | D70: Denied | E70: Sound that operation avoid morning their. | G70: POL63440106 | H70: =_xlfn.XLOOKUP(Claims!$G70,Table1[Policy ID],Table1[Policy Type]) -> Health
A71: CLM50724959 | B71: 45515 | C71: 4529 | D71: Denied | E71: Simple other role not. | F71: 45605 | G71: POL59354713 | H71: =_xlfn.XLOOKUP(Claims!$G71,Table1[Policy ID],Table1[Policy Type]) -> Life
A72: CLM33888157 | B72: 44174 | C72: 54069 | D72: Pending | E72: Response it six realize doctor. | G72: POL77625425 | H72: =_xlfn.XLOOKUP(Claims!$G72,Table1[Policy ID],Table1[Policy Type]) -> Life
A73: CLM51474654 | B73: 45035 | C73: 10870 | D73: Pending | E73: Staff carry address. | F73: 45084 | G73: POL18831547 | H73: =_xlfn.XLOOKUP(Claims!$G73,Table1[Policy ID],Table1[Policy Type]) -> Life
A74: CLM93171228 | B74: 45592 | C74: 67443 | D74: Approved | E74: Theory window see soon. | F74: 45629 | G74: POL24534591 | H74: =_xlfn.XLOOKUP(Claims!$G74,Table1[Policy ID],Table1[Policy Type]) -> Health
A75: CLM43392789 | B75: 43872 | C75: 4636 | D75: Denied | E75: Natural tell whole scientist why weight receive. | F75: 43900 | G75: POL54483538 | H75: =_xlfn.XLOOKUP(Claims!$G75,Table1[Policy ID],Table1[Policy Type]) -> Auto
A76: CLM88894585 | B76: 44127 | C76: 11566 | D76: Approved | E76: One foreign space whether mother. | F76: 44185 | G76: POL55300155 | H76: =_xlfn.XLOOKUP(Claims!$G76,Table1[Policy ID],Table1[Policy Type]) -> Property
A77: CLM07858710 | B77: 45362 | C77: 23913 | D77: Denied | E77: Kitchen talk throw. | F77: 45381 | G77: POL82812319 | H77: =_xlfn.XLOOKUP(Claims!$G77,Table1[Policy ID],Table1[Policy Type]) -> Property
A78: CLM97170433 | B78: 44408 | C78: 23354 | D78: Approved | E78: Prevent we project hit oil church. | F78: 44429 | G78: POL33244868 | H78: =_xlfn.XLOOKUP(Claims!$G78,Table1[Policy ID],Table1[Policy Type]) -> Life
A79: CLM31270051 | B79: 44704 | C79: 94795 | D79: Approved | E79: Name any option into western final. | F79: 44744 | G79: POL74496346 | H79: =_xlfn.XLOOKUP(Claims!$G79,Table1[Policy ID],Table1[Policy Type]) -> Auto
A80: CLM82267397 | B80: 44269 | C80: 11923 | D80: Pending | E80: Push finally hair. | F80: 44284 | G80: POL18917162 | H80: =_xlfn.XLOOKUP(Claims!$G80,Table1[Policy ID],Table1[Policy Type]) -> Health
A81: CLM25622565 | B81: 45315 | C81: 20013 | D81: Denied | E81: Would level despite imagine. | F81: 45391 | G81: POL98789630 | H81: =_xlfn.XLOOKUP(Claims!$G81,Table1[Policy ID],Table1[Policy Type]) -> Life
A82: CLM64484686 | B82: 45068 | C82: 6157 | D82: Approved | E82: Our full outside policy. | F82: 45147 | G82: POL47427298 | H82: =_xlfn.XLOOKUP(Claims!$G82,Table1[Policy ID],Table1[Policy Type]) -> Health
A83: CLM38705286 | B83: 44232 | C83: 63821 | D83: Denied | E83: Camera start really benefit risk security article. | G83: POL76589663 | H83: =_xlfn.XLOOKUP(Claims!$G83,Table1[Policy ID],Table1[Policy Type]) -> Life
A84: CLM23146923 | B84: 45127 | C84: 19885 | D84: Approved | E84: Top center exist action. | G84: POL12935594 | H84: =_xlfn.XLOOKUP(Claims!$G84,Table1[Policy ID],Table1[Policy Type]) -> Property
A85: CLM24301039 | B85: 44139 | C85: 47975 | D85: Denied | E85: While character eat expect. | G85: POL55835566 | H85: =_xlfn.XLOOKUP(Claims!$G85,Table1[Policy ID],Table1[Policy Type]) -> Health
A86: CLM15657898 | B86: 44676 | C86: 98275 | D86: Denied | E86: Act others many weight. | F86: 44721 | G86: POL91241306 | H86: =_xlfn.XLOOKUP(Claims!$G86,Table1[Policy ID],Table1[Policy Type]) -> Auto
A87: CLM64734849 | B87: 44922 | C87: 7732 | D87: Approved | E87: South detail energy somebody coach. | G87: POL10073827 | H87: =_xlfn.XLOOKUP(Claims!$G87,Table1[Policy ID],Table1[Policy Type]) -> Life
A88: CLM93105620 | B88: 44199 | C88: 25294 | D88: Denied | E88: Event fund less country special. | F88: 44215 | G88: POL43123760 | H88: =_xlfn.XLOOKUP(Claims!$G88,Table1[Policy ID],Table1[Policy Type]) -> Property
A89: CLM64154491 | B89: 43950 | C89: 4473 | D89: Pending | E89: These series movement international toward change movie yard. | F89: 43978 | G89: POL45095642 | H89: =_xlfn.XLOOKUP(Claims!$G89,Table1[Policy ID],Table1[Policy Type]) -> Property
A90: CLM33798304 | B90: 45186 | C90: 28593 | D90: Denied | E90: Newspaper season me. | F90: 45208 | G90: POL81122472 | H90: =_xlfn.XLOOKUP(Claims!$G90,Table1[Policy ID],Table1[Policy Type]) -> Life
A91: CLM14944933 | B91: 44088 | C91: 96104 | D91: Pending | E91: Instead hit field manager difference face will. | G91: POL95405693 | H91: =_xlfn.XLOOKUP(Claims!$G91,Table1[Policy ID],Table1[Policy Type]) -> Property
A92: CLM95099823 | B92: 44045 | C92: 65503 | D92: Pending | E92: Him book heart still. | G92: POL20670070 | H92: =_xlfn.XLOOKUP(Claims!$G92,Table1[Policy ID],Table1[Policy Type]) -> Auto
A93: CLM39666392 | B93: 44479 | C93: 65199 | D93: Pending | E93: Ball not yet get apply. | F93: 44495 | G93: POL84424949 | H93: =_xlfn.XLOOKUP(Claims!$G93,Table1[Policy ID],Table1[Policy Type]) -> Life
A94: CLM25529207 | B94: 44475 | C94: 80432 | D94: Denied | E94: Imagine seat friend office it. | F94: 44527 | G94: POL56083774 | H94: =_xlfn.XLOOKUP(Claims!$G94,Table1[Policy ID],Table1[Policy Type]) -> Property
A95: CLM45018730 | B95: 44273 | C95: 92471 | D95: Approved | E95: Rule memory around international building national. | F95: 44314 | G95: POL50239325 | H95: =_xlfn.XLOOKUP(Claims!$G95,Table1[Policy ID],Table1[Policy Type]) -> Health
A96: CLM16989357 | B96: 44015 | C96: 62441 | D96: Pending | E96: Able attention our change section rock usually already. | G96: POL66167857 | H96: =_xlfn.XLOOKUP(Claims!$G96,Table1[Policy ID],Table1[Policy Type]) -> Life
A97: CLM73336882 | B97: 45486 | C97: 84687 | D97: Approved | E97: Possible water guess million. | G97: POL44119689 | H97: =_xlfn.XLOOKUP(Claims!$G97,Table1[Policy ID],Table1[Policy Type]) -> Property
A98: CLM98110295 | B98: 44210 | C98: 44110 | D98: Denied | E98: Community dog join brother. | F98: 44274 | G98: POL91286503 | H98: =_xlfn.XLOOKUP(Claims!$G98,Table1[Policy ID],Table1[Policy Type]) -> Property
A99: CLM49151950 | B99: 45302 | C99: 42149 | D99: Denied | E99: Measure partner professor real trouble enter western president. | G99: POL83969664 | H99: =_xlfn.XLOOKUP(Claims!$G99,Table1[Policy ID],Table1[Policy Type]) -> Property
A100: CLM62334592 | B100: 44776 | C100: 8683 | D100: Denied | E100: Expert near owner. | G100: POL76937321 | H100: =_xlfn.XLOOKUP(Claims!$G100,Table1[Policy ID],Table1[Policy Type]) -> Life
...

Sheet Payment History
A1: Payment ID | B1: Date of Payment | C1: Amount Paid | D1: Payment Method | E1: Payment Status | F1: Policy ID
A2: PAY00503494 | B2: 45338 | C2: 1121.13 | D2: Cash | E2: Successful | F2: POL09901587
A3: PAY78887551 | B3: 44945 | C3: 1420.69 | D3: Bank Transfer | E3: Successful | F3: POL73324138
A4: PAY14700139 | B4: 45138 | C4: 490.76 | D4: Cash | E4: Successful | F4: POL71278302
A5: PAY00915248 | B5: 44658 | C5: 1150.59 | D5: Cash | E5: Failed | F5: POL24753734
A6: PAY94123626 | B6: 44778 | C6: 1490.26 | D6: Cash | E6: Failed | F6: POL18290935
A7: PAY53415430 | B7: 45540 | C7: 1318.96 | D7: Credit Card | E7: Failed | F7: POL98372511
A8: PAY84843365 | B8: 45187 | C8: 158.43 | D8: Cash | E8: Failed | F8: POL20843719
A9: PAY97836039 | B9: 45196 | C9: 994.21 | D9: Credit Card | E9: Failed | F9: POL03845436
A10: PAY65075228 | B10: 44965 | C10: 233.3 | D10: Bank Transfer | E10: Successful | F10: POL70775475
A11: PAY17334868 | B11: 45457 | C11: 176.91 | D11: Bank Transfer | E11: Failed | F11: POL23603808
A12: PAY39650460 | B12: 44903 | C12: 513.88 | D12: Cash | E12: Failed | F12: POL52535973
A13: PAY81033711 | B13: 45545 | C13: 380.15 | D13: Credit Card | E13: Failed | F13: POL52256054
... A5001: PAY74470147 | B5001: 45027 | C5001: 186.4 | D5001: Cash | E5001: Successful | F5001: POL54989284

Sheet Additional Fields
A1: Agent ID | B1: Renewal Status | C1: Policy Discounts | D1: Risk Score | E1: Policy ID
A2: AGT43228742 | B2: Not Renewed | C2: 31 | D2: 42 | E2: POL27806251
A3: AGT46808172 | B3: Pending | C3: 12 | D3: 76 | E3: POL96934398
A4: AGT32340750 | B4: Pending | C4: 17 | D4: 5 | E4: POL93505220
A5: AGT68647921 | B5: Not Renewed | C5: 18 | D5: 80 | E5: POL39531025
A6: AGT57092464 | B6: Pending | C6: 28 | D6: 1 | E6: POL38769300
A7: AGT47653967 | B7: Renewed | C7: 25 | D7: 36 | E7: POL07841878
A8: AGT05457971 | B8: Not Renewed | C8: 2 | D8: 99 | E8: POL21963992
A9: AGT63127637 | B9: Not Renewed | C9: 13 | D9: 100 | E9: POL64589705
A10: AGT49332725 | B10: Not Renewed | C10: 7 | D10: 35 | E10: POL49133977
A11: AGT70109277 | B11: Not Renewed | C11: 9 | D11: 64 | E11: POL80278196
A12: AGT41262935 | B12: Pending | C12: 11 | D12: 80 | E12: POL89935970
A13: AGT39802391 | B13: Not Renewed | C13: 14 | D13: 41 | E13: POL40425029
... A5001: AGT29267388 | B5001: Not Renewed | C5001: 25 | D5001: 38 | E5001: POL16711858

Sheet KPI 1
A1: Status | B1: Count of Policy ID
A2: Active | B2: 1682
A3: Terminated | B3: 1678
A4: Lapsed | B4: 1640
A5: Grand Total | B5: 5000

Sheet KPI 2
A1: Row Labels | B1: Count of Customer ID
A2: CUST00111093 | B2: 2
A3: CUST00125540 | B3: 2
A4: CUST00150301 | B4: 2
A5: CUST00157628 | B5: 1
A6: CUST00163744 | B6: 2
A7: CUST00235004 | B7: 1
A8: CUST00277838 | B8: 1
A9: CUST00283741 | B9: 3
A10: CUST00359219 | B10: 1
A11: CUST00376151 | B11: 2
A12: CUST00428034 | B12: 2
A13: CUST00432697 | B13: 1
... A3150: Grand Total | B3150: 5000

Sheet KPI 3
A4: Age Bucket | B4: Count of Policy ID
A5: 18-25 | B5: 572
A6: 36-45 | B6: 706
A7: 46-55 | B7: 737
A8: 26-35 | B8: 805
A9: 56+ | B9: 2180
A10: Grand Total | B10: 5000

Sheet KPI 4
A1: Gender | B1: Count of Policy ID
A2: Female | B2: 1624
A3: Male | B3: 1677
A4: Other | B4: 1699
A5: Grand Total | B5: 5000

Sheet KPI 5
A1: Policy Type | B1: Count of Policy ID
A2: Health | B2: 1316
A3: Property | B3: 1236
A4: Life | B4: 1234
A5: Auto | B5: 1214
A6: Grand Total | B6: 5000

Sheet KPI 6
A1: Years (Policy End Date) | B1: Count of Policy ID
A2: 2016 | B2: 25
A3: 2017 | B3: 77
A4: 2018 | B4: 142
A5: 2019 | B5: 178
A6: 2020 | B6: 262
A7: 2021 | B7: 309
A8: 2022 | B8: 371
A9: 2023 | B9: 418
A10: 2024 | B10: 454
A11: 2025 | B11: 526
A12: 2026 | B12: 453
A13: 2027 | B13: 422
... A21: Grand Total | B21: 5000

Sheet 7
A1: Years (Policy Start Date) | B1: Sum of Premium Amount
A2: 2014
A3: 2015 | B3: 38.549689
A4: 2016 | B4: 0.059111657
A5: 2017 | B5: -0.068976908
A6: 2018 | B6: 0.001039125
A7: 2019 | B7: 0.010145225
A8: 2020 | B8: -0.019600494
A9: 2021 | B9: 0.01162231
A10: 2022 | B10: 0.075316046
A11: 2023 | B11: -0.093854224
A12: 2024 | B12: -0.067032566

Sheet KPI 7
A1: Year | B1: Sum of Premium Amount
A2: 2014
A3: 2015 | B3: 38.549689
A4: 2016 | B4: 0.059111657
A5: 2017 | B5: -0.068976908
A6: 2018 | B6: 0.001039125
A7: 2019 | B7: 0.010145225
A8: 2020 | B8: -0.019600494
A9: 2021 | B9: 0.01162231
A10: 2022 | B10: 0.075316046
A11: 2023 | B11: -0.093854224
A12: 2024 | B12: -0.067032566

Sheet KPI 8
A1: Claim Status | B1: Count of Policy ID
A2: Approved | B2: 1712
A3: Denied | B3: 1638
A4: Pending | B4: 1650
A5: Grand Total | B5: 5000

Sheet KPI 9
A1: Payment Status | B1: Count of Policy ID
A2: Failed | B2: 2484
A3: Successful | B3: 2516
A4: Grand Total | B4: 5000

Sheet KPI 10
A1: Sum of Claim Amount
A2: 251378846 | B2: 251378846

Sheet Sheet20
A1: Payment Method | B1: Count of Policy ID
A2: Bank Transfer | B2: 1645
A3: Cash | B3: 1744
A4: Credit Card | B4: 1611
A5: Grand Total | B5: 5000

Sheet Sheet21
A1: Renewal Status | B1: Count of Policy ID
A2: Not Renewed | B2: 1685
A3: Pending | B3: 1647
A4: Renewed | B4: 1668
A5: Grand Total | B5: 5000

Sheet Sheet22
A1: Payment Frequency | B1: Count of Customer ID
A2: Quarterly | B2: 1711
A3: Annually | B3: 1649
A4: Monthly | B4: 1640
A5: Grand Total | B5: 5000

Sheet Sheet23
A1: Year | B1: Count of Customer ID
A2: 2014 | B2: 0.0022
A3: 2015 | B3: 0.0964
A4: 2016 | B4: 0.1074
A5: 2017 | B5: 0.0964
A6: 2018 | B6: 0.1004
A7: 2019 | B7: 0.0998
A8: 2020 | B8: 0.1016
A9: 2021 | B9: 0.0992
A10: 2022 | B10: 0.1018
A11: 2023 | B11: 0.0988
A12: 2024 | B12: 0.096
A13: Grand Total | B13: 1

Sheet Dashboard

Sheet Policy

Sheet Payment
